<root>
   <quiz>
      <maths>
         <q1>
            <question>5 + 7 = ?</question>
			<answer>12</answer>
			<options>
               <element>10</element>
               <element>11</element>
               <element>12</element>
               <element>13</element>
            </options>
         </q1>
         <q2>
            <question>12 - 8 = ?</question>
            <options>
               <element>1</element>
               <element>2</element>
               <element>3</element>
               <element>4</element>
            </options>
			<answer>4</answer>
         </q2>
      </maths>
      <sport>
         <q1>
            <question>Which one is correct team name in NBA?</question>
            <options>
               <element>New York Bulls</element>
               <element>Los Angeles Kings</element>
               <element>Golden State Warriros</element>
               <element>Huston Rocket</element>
            </options>
			<answer>Huston Rocket</answer>
         </q1>
      </sport>
   </quiz>
</root>